{
  "directed": true,
  "multigraph": false,
  "graph": {},
  "nodes": [
    {
      "type": "CORE",
      "rotation": "DEG_0",
      "raw_id": 5426010000,
      "id": 0
    },
    {
      "type": "HINGE",
      "rotation": "DEG_315",
      "raw_id": 5426012832,
      "id": 1
    },
    {
      "type": "BRICK",
      "rotation": "DEG_135",
      "raw_id": 5426012448,
      "id": 2
    },
    {
      "type": "HINGE",
      "rotation": "DEG_135",
      "raw_id": 5426012688,
      "id": 3
    },
    {
      "type": "HINGE",
      "rotation": "DEG_270",
      "raw_id": 5426011728,
      "id": 4
    },
    {
      "type": "HINGE",
      "rotation": "DEG_135",
      "raw_id": 5426012592,
      "id": 5
    },
    {
      "type": "HINGE",
      "rotation": "DEG_90",
      "raw_id": 5426012304,
      "id": 6
    }
  ],
  "edges": [
    {
      "face": "BACK",
      "source": 0,
      "target": 1
    },
    {
      "face": "FRONT",
      "source": 1,
      "target": 2
    },
    {
      "face": "FRONT",
      "source": 2,
      "target": 3
    },
    {
      "face": "LEFT",
      "source": 2,
      "target": 5
    },
    {
      "face": "BOTTOM",
      "source": 2,
      "target": 6
    },
    {
      "face": "FRONT",
      "source": 3,
      "target": 4
    }
  ]
}